{
    "tag":  "chkpt-f2-6b7cd45",
    "files":  [
                  "data/blueprints/LYNN-001.sample.placeholder.txt",
                  "docs/ESTIMATING_PIPELINE.md",
                  "openapi/contracts/takeoff.v1.contract.json",
                  "requirements.txt",
                  "schemas/takeoff_request.schema.json",
                  "schemas/takeoff_response.schema.json",
                  "scripts/smoke_takeoff_v1.ps1",
                  "tests/unit/test_takeoff_engine.py",
                  "web/backend/app_comprehensive.py",
                  "web/backend/blueprint_parsers/pdf_titleblock.py",
                  "web/backend/takeoff_engine.py"
              ],
    "remote_head":  "6b7cd45e3dc985ecc30a4e0b9e408a38abde7165",
    "branch":  "master",
    "result":  "pushed",
    "time":  "2025-11-07T11:44:16-05:00",
    "local_head":  "6b7cd45e3dc985ecc30a4e0b9e408a38abde7165"
}
